pyapnea/__init__.py
pyapnea/base_functions.py
pyapnea/oscar/__init__.py
pyapnea/oscar/data_structure.py
pyapnea/oscar/oscar_constants.py
pyapnea/oscar/oscar_getter.py
pyapnea/oscar/oscar_loader.py
pyapnea/pytorch/__init__.py
pyapnea/pytorch/raw_oscar_dataset.py
pyapnea/utils/__init__.py
pyapnea/utils/annotations.py
pyapnea-0.1.dist-info/LICENSE
pyapnea-0.1.dist-info/METADATA
pyapnea-0.1.dist-info/WHEEL
pyapnea-0.1.dist-info/top_level.txt
pyapnea-0.1.dist-info/RECORD
