Metadata-Version: 2.1
Name: pyapnea
Version: 0.1
Summary: Python package related to Apnea data analysis
Author-email: Julien Laumonier <julien.laumonier@iid.ulaval.ca>
Project-URL: Homepage, https://github.com/iid-ulaval/pyapnea
Project-URL: Bug Tracker, https://github.com/iid-ulaval/pyapnea/issues
Project-URL: Documentation, https://pyapnea.readthedocs.io/en/latest/
Classifier: Programming Language :: Python :: 3
Classifier: License :: OSI Approved :: GNU General Public License v3 (GPLv3)
Classifier: Operating System :: OS Independent
Requires-Python: >=3.10
License-File: LICENSE
